igipy/__init__.py
igipy/__main__.py
igipy/cli.py
igipy/config.py
igipy/managers.py
igipy/utils.py
igipy/bin/README.md
igipy/bin/gconv.exe
igipy/bin/gconvapi.dll
igipy/bin/vqdll.dll
igipy/formats/__init__.py
igipy/formats/base.py
igipy/formats/ilff.py
igipy/formats/mef.py
igipy/formats/qsc.py
igipy/formats/qvm.py
igipy/formats/res.py
igipy/formats/tex.py
igipy/formats/tga.py
igipy/formats/wav.py
igipy/formats/utils/__init__.py
igipy/formats/utils/adpcm.py
igipy-0.2.2.dist-info/METADATA
igipy-0.2.2.dist-info/WHEEL
igipy-0.2.2.dist-info/entry_points.txt
igipy-0.2.2.dist-info/RECORD
