Metadata-Version: 2.4
Name: igipy
Version: 0.2.2
Summary: Reverse engineering tools for 'Project IGI' game
Author-email: "artiom.rotari" <artiom.rotari@ebs-integrator.com>
Requires-Python: >=3.13
Requires-Dist: numpy>=2.3.1
Requires-Dist: pydantic>=2.11.7
Requires-Dist: typer>=0.16.0
